{
  "window_title": "梦幻西游",
  "input_backend": "sendinput",
  "window_offset": [0, 0],
  "hotkey_toggle": "F5",
  "humanize": {
    "speed": 2.0,
    "snipe_speed": 5.0,
    "click_radius": 4,
    "px_per_step": 12,
    "interval_jitter": 0.4,
    "idle_chance": 0.0,
    "idle_min_sec": 1.5,
    "idle_max_sec": 5.0
  },
  "hotkeys": {
    "close_panel": ["esc"],
    "open_bag": ["alt", "e"],
    "open_task": ["alt", "y"],
    "open_activity": ["alt", "c"],
    "open_character": ["alt", "w"],
    "open_skill": ["alt", "s"],
    "open_summon": ["alt", "q"],
    "open_team": ["alt", "t"],
    "open_friend": ["alt", "f"],
    "open_rank": ["alt", "r"],
    "open_map": ["alt", "m"],
    "open_minimap": ["tab"],
    "open_system": ["alt", "j"],
    "open_mount": ["alt", "k"],
    "open_guide": ["alt", "h"],
    "open_shop": ["alt", "a"],
    "open_welfare": ["alt", "d"],
    "open_strengthen": ["alt", "v"],
    "open_guild": ["alt", "b"],
    "open_home": ["alt", "n"],
    "open_helper": ["alt", "z"],
    "open_chat": ["alt", "x"],
    "hide_ui": ["alt", "p"],
    "afk": ["alt", "g"],
    "boss_key": ["alt", "l"],
    "pin_window": ["alt", "u"]
  },
  "game_hotkeys": {
    "field": {
      "f7": "横竖屏切换", "tab": "小地图",
      "alt+q": "召唤灵", "alt+w": "人物", "alt+e": "包裹", "alt+r": "排行",
      "alt+t": "队伍", "alt+y": "任务", "alt+u": "置顶客户端", "alt+p": "隐藏界面",
      "alt+a": "商城", "alt+s": "技能", "alt+d": "福利", "alt+f": "好友",
      "alt+g": "挂机", "alt+h": "指引", "alt+j": "系统", "alt+k": "坐骑", "alt+l": "老板键",
      "alt+z": "助战", "alt+x": "聊天", "alt+c": "活动", "alt+v": "强化",
      "alt+b": "帮派", "alt+n": "家园", "alt+m": "大地图"
    },
    "battle": {
      "f7": "横竖屏切换",
      "alt+q": "默认随机法术", "alt+w": "法术", "alt+e": "道具", "alt+r": "召唤",
      "alt+t": "保护", "alt+y": "任务", "alt+u": "置顶客户端",
      "alt+a": "攻击", "alt+s": "默认法术", "alt+d": "防御", "alt+f": "好友",
      "alt+g": "捕捉", "alt+h": "指引", "alt+j": "系统", "alt+k": "坐骑", "alt+l": "老板键",
      "alt+z": "特技", "alt+x": "聊天", "alt+c": "法宝", "alt+v": "强化",
      "alt+b": "帮派", "alt+n": "家园"
    }
  },
  "tasks": {
    "sniper": {
      "dry_run": true,
      "loop": {
        "refresh_interval_sec": 0.2,
        "shelf_load_wait_sec": 1.2,
        "shelf_load_min_sec": 0.15,
        "match_threshold": 0.85,
        "after_buy_cooldown_sec": 2.0
      },
      "regions": {
        "listing": [120, 200, 600, 360],
        "category_button": [40, 240, 96, 36],
        "product_entry": [180, 300, 160, 40],
        "buy_button": [760, 480, 90, 36],
        "confirm_button": [430, 360, 100, 40]
      },
      "watchlist": [
        { "name": "wujibie_xianglian", "template": "templates/wujibie_xianglian.png", "max_price": null }
      ]
    },
    "treasure_map": {
      "dry_run": true,
      "skip_collect": false,
      "loop": {
        "time_limit_min": 30,
        "match_threshold": 0.85,
        "tick_interval_sec": 0.6,
        "still_min_sec": 0.3,
        "still_wait_sec": 2.0,
        "still_diff": 8.0,
        "collect_idle_sec": 4.0,
        "activity_timeout_sec": 30,
        "dialog_timeout_sec": 30,
        "collect_timeout_sec": 600,
        "dig_timeout_sec": 120,
        "scroll_step": -3,
        "scroll_max_tries": 8,
        "max_stuck_recover": 3
      },
      "regions": {
        "scene": [0, 0, 1024, 768],
        "activity_list": [600, 200, 360, 420],
        "bag_list": [560, 220, 380, 360]
      },
      "templates": {
        "flag_treasure_entry": "templates/tm_flag_treasure_entry.png",
        "flag_join": "templates/tm_flag_join.png",
        "flag_tingting": "templates/tm_flag_tingting.png",
        "flag_battle": "templates/tm_flag_battle.png",
        "flag_next_map": "templates/tm_flag_next_map.png",
        "treasure_item": "templates/tm_treasure_item.png"
      }
    }
  }
}
